src/__init__.py
src/csv_IO.py
src/dataMatrix.py
src/diversity.py
src/graphics.py
src/groups.py
src/null.py
src/statFunctions.py
powerball-0.2.4.dist-info/LICENSE
powerball-0.2.4.dist-info/METADATA
powerball-0.2.4.dist-info/WHEEL
powerball-0.2.4.dist-info/top_level.txt
powerball-0.2.4.dist-info/RECORD
