Metadata-Version: 2.1
Name: powerball
Version: 0.2.4
Summary: A tool for competitive lottery analysis of bacterial groups.
Home-page: https://github.com/mmarshall124/powerball
Author: Matthew Marshall
Author-email: matthewmarshall124@gmail.com
License: MIT
Platform: UNKNOWN
Classifier: Programming Language :: Python :: 3
Classifier: License :: OSI Approved :: MIT License
Classifier: Operating System :: OS Independent
Classifier: Development Status :: 3 - Alpha
Classifier: Environment :: Console
Classifier: Topic :: Scientific/Engineering :: Bio-Informatics
